facebook_downloader/__init__.py
facebook_downloader/downloader.py
facebook_downloader/main.py
facebook_downloader-2022.1.2.1.dist-info/LICENSE
facebook_downloader-2022.1.2.1.dist-info/METADATA
facebook_downloader-2022.1.2.1.dist-info/WHEEL
facebook_downloader-2022.1.2.1.dist-info/entry_points.txt
facebook_downloader-2022.1.2.1.dist-info/top_level.txt
facebook_downloader-2022.1.2.1.dist-info/RECORD
